Workbook
Name BasicPlan_Growth: Inputs!$C$5
Name BasicPlanPrice: Inputs!$C$11
Name Beg_InactiveSubs: Inputs!$C$10
Name BegActiveSubs: Inputs!$C$7
Name BegBasicSubs: Inputs!$C$8
Name BegPremiumSubs: Inputs!$C$9
Name CAC: Inputs!$C$14
Name GrossMarginPercent: Inputs!$C$13
Name New_Signups: Inputs!$C$2
Name P_Matrix: Inputs!$F$17:$I$20
Name PremiumPlan_Grwoth: Inputs!$C$6
Name PremiumPlanPrice: Inputs!$C$12
Name Time_Horizon: Inputs!$C$15

Sheet Inputs
A1: Inputs
A2: Subscriber Growth | B2: New Signups (Month 1) | C2: 20000
B3: New Signups Growth Per Month | C3: 0.01
B4: The Month Growth Flattens Out | C4: 500
B5: Basic Plan Growth Share | C5: 0.7
B6: Premium Plan Growth Share | C6: 0.3
A7: Initial Subscriber Spread | B7: Beginning Active Subscribers | C7: 1000000
B8: Beginning Basic Plan Customers % | C8: 0.64
B9: Beginning Premium Plan Customers % | C9: 0.33
B10: Beginning Inactive Customers % | C10: =1-(C9+C8) -> 0.03
A11: Pricing | B11: Basic Plan Monthly Price | C11: 15
B12: Premium Plan Monthly Price | C12: 22
B13: Gross Margin % | C13: 0.45
B14: Customer Acquisition Cost | C14: 120
E15: Probability Matrix
E16: Value | F16: Basic Plan | G16: Premium Plan | H16: Inactive | I16: Churned
E17: Basic Plan | F17: 0.94 | G17: 0.02 | H17: 0.01 | I17: 0.03
E18: Premium Plan | F18: 0.01 | G18: 0.95 | H18: 0.01 | I18: 0.03
E19: Inactive | F19: 0.1 | G19: 0.05 | H19: 0.6 | I19: 0.25
E20: Churned | F20: 0 | G20: 0 | H20: 0 | I20: 1
E23: Population Growth Vector (Month 1)
F24: Basic Plan | G24: Premium Plan | H24: Inactive | I24: Churned
F25: =C5*C2 -> 14000 | G25: =C6*C2 -> 6000 | H25: 0 | I25: 0
E27: Initial Subscriber Vector (Month 0)
F28: Basic Plan | G28: Premium Plan | H28: Inactive | I28: Churned
F29: =C7*C8 -> 640000 | G29: =C7*C9 -> 330000 | H29: =C10*C7 -> 30000 | I29: 0

Sheet Steady State
A1: Month | C1: Basic Plan | D1: Premium Plan | E1: Inactive | F1: Churned | H1: Mmult Engine | M1: Population Growth
A2: 0 | C2: =Inputs!F29 -> 640000 | D2: =Inputs!G29 -> 330000 | E2: =Inputs!H29 -> 30000 | F2: =Inputs!I29 -> 0 | H2: Basic Plan | I2: Premium Plan | J2: Inactive | K2: Churned | M2: Basic Plan | N2: Premium Plan | O2: Inactive | P2: Churned
A3: 1 | C3: =H3+M3 -> 621900 | D3: =I3+N3 -> 333800 | E3: =J3+O3 -> 27700 | F3: =(K3+P3)-F2 -> 36600 | H3: {=MMULT($C2:$F2,P_Matrix)} -> 607900 | I3: 327800 | J3: 27700 | K3: 36600 | M3: =(Inputs!F$25*POWER(1+(Inputs!$C$3-(Inputs!$C$3*(('Steady State'!$A3-1)/Inputs!$C$4))),'Steady State'!$A3-1)) -> 14000 | N3: =(Inputs!G$25*POWER(1+(Inputs!$C$3-(Inputs!$C$3*(('Steady State'!$A3-1)/Inputs!$C$4))),'Steady State'!$A3-1)) -> 6000 | O3: =(Inputs!H$25*POWER(1+(Inputs!$C$3-(Inputs!$C$3*(('Steady State'!$A3-1)/Inputs!$C$4))),'Steady State'!$A3-1)) -> 0 | P3: =(Inputs!I$25*POWER(1+(Inputs!$C$3-(Inputs!$C$3*(('Steady State'!$A3-1)/Inputs!$C$4))),'Steady State'!$A3-1)) -> 0
A4: 2 | C4: =H4+M4 -> 604833.72 | D4: =I4+N4 -> 336992.88 | E4: =J4+O4 -> 26177 | F4: =(K4+P4)-F3 -> 35596 | H4: {=MMULT($C3:$F3,P_Matrix)} -> 590694 | I4: 330933 | J4: 26177 | K4: 72196 | M4: =MAX((Inputs!F$25*POWER(1+(Inputs!$C$3-(Inputs!$C$3*(('Steady State'!$A4-1)/Inputs!$C$4))),'Steady State'!$A4-1)),M3) -> 14139.72 | N4: =MAX((Inputs!G$25*POWER(1+(Inputs!$C$3-(Inputs!$C$3*(('Steady State'!$A4-1)/Inputs!$C$4))),'Steady State'!$A4-1)),N3) -> 6059.88 | O4: =MAX((Inputs!H$25*POWER(1+(Inputs!$C$3-(Inputs!$C$3*(('Steady State'!$A4-1)/Inputs!$C$4))),'Steady State'!$A4-1)),O3) -> 0 | P4: =MAX((Inputs!I$25*POWER(1+(Inputs!$C$3-(Inputs!$C$3*(('Steady State'!$A4-1)/Inputs!$C$4))),'Steady State'!$A4-1)),P3) -> 0
A5: 3 | C5: =H5+M5 -> 588811.59 | D5: =I5+N5 -> 339668.88 | E5: =J5+O5 -> 25124.466 | F5: =(K5+P5)-F4 -> 34799.048 | H5: {=MMULT($C4:$F4,P_Matrix)} -> 574531.33 | I5: 333548.76 | J5: 25124.466 | K5: 70395.048 | M5: =MAX((Inputs!F$25*POWER(1+(Inputs!$C$3-(Inputs!$C$3*(('Steady State'!$A5-1)/Inputs!$C$4))),'Steady State'!$A5-1)),M4) -> 14280.269 | N5: =MAX((Inputs!G$25*POWER(1+(Inputs!$C$3-(Inputs!$C$3*(('Steady State'!$A5-1)/Inputs!$C$4))),'Steady State'!$A5-1)),N4) -> 6120.1152 | O5: 0 | P5: 0
A6: 4 | C6: =H6+M6 -> 573813.68 | D6: =I6+N6 -> 341898.59 | E6: =J6+O6 -> 24359.484 | F6: =(K6+P6)-F5 -> 34135.531 | H6: {=MMULT($C5:$F5,P_Matrix)} -> 559392.03 | I6: 335717.89 | J6: 24359.484 | K6: 68934.579 | M6: =MAX((Inputs!F$25*POWER(1+(Inputs!$C$3-(Inputs!$C$3*(('Steady State'!$A6-1)/Inputs!$C$4))),'Steady State'!$A6-1)),M5) -> 14421.644 | N6: =MAX((Inputs!G$25*POWER(1+(Inputs!$C$3-(Inputs!$C$3*(('Steady State'!$A6-1)/Inputs!$C$4))),'Steady State'!$A6-1)),N5) -> 6180.7044 | O6: 0 | P6: 0
A7: 5 | C7: =H7+M7 -> 559803.63 | D7: =I7+N7 -> 343739.56 | E7: =J7+O7 -> 23772.813 | F7: =(K7+P7)-F6 -> 33561.239 | H7: {=MMULT($C6:$F6,P_Matrix)} -> 545239.79 | I7: 337497.91 | J7: 23772.813 | K7: 67696.77 | M7: =MAX((Inputs!F$25*POWER(1+(Inputs!$C$3-(Inputs!$C$3*(('Steady State'!$A7-1)/Inputs!$C$4))),'Steady State'!$A7-1)),M6) -> 14563.841 | N7: =MAX((Inputs!G$25*POWER(1+(Inputs!$C$3-(Inputs!$C$3*(('Steady State'!$A7-1)/Inputs!$C$4))),'Steady State'!$A7-1)),N6) -> 6241.6461 | O7: 0 | P7: 0
A8: 6 | C8: =H8+M8 -> 546736.95 | D8: =I8+N8 -> 345240.23 | E8: =J8+O8 -> 23299.12 | F8: =(K8+P8)-F7 -> 33049.499 | H8: {=MMULT($C7:$F7,P_Matrix)} -> 532030.09 | I8: 338937.29 | J8: 23299.12 | K8: 66610.738 | M8: =MAX((Inputs!F$25*POWER(1+(Inputs!$C$3-(Inputs!$C$3*(('Steady State'!$A8-1)/Inputs!$C$4))),'Steady State'!$A8-1)),M7) -> 14706.858 | N8: =MAX((Inputs!G$25*POWER(1+(Inputs!$C$3-(Inputs!$C$3*(('Steady State'!$A8-1)/Inputs!$C$4))),'Steady State'!$A8-1)),N7) -> 6302.9391 | O8: 0 | P8: 0
A9: 7 | C9: =H9+M9 -> 534565.74 | D9: =I9+N9 -> 346442.5 | E9: =J9+O9 -> 22899.244 | F9: =(K9+P9)-F8 -> 32584.095 | H9: {=MMULT($C8:$F8,P_Matrix)} -> 519715.05 | I9: 340077.91 | J9: 22899.244 | K9: 65633.594 | M9: =MAX((Inputs!F$25*POWER(1+(Inputs!$C$3-(Inputs!$C$3*(('Steady State'!$A9-1)/Inputs!$C$4))),'Steady State'!$A9-1)),M8) -> 14850.691 | N9: =MAX((Inputs!G$25*POWER(1+(Inputs!$C$3-(Inputs!$C$3*(('Steady State'!$A9-1)/Inputs!$C$4))),'Steady State'!$A9-1)),N8) -> 6364.5819 | O9: 0 | P9: 0
A10: 8 | C10: =H10+M10 -> 523241.48 | D10: =I10+N10 -> 347383.22 | E10: =J10+O10 -> 22549.629 | F10: =(K10+P10)-F9 -> 32155.058 | H10: {=MMULT($C9:$F9,P_Matrix)} -> 508246.14 | I10: 340956.65 | J10: 22549.629 | K10: 64739.153 | M10: =MAX((Inputs!F$25*POWER(1+(Inputs!$C$3-(Inputs!$C$3*(('Steady State'!$A10-1)/Inputs!$C$4))),'Steady State'!$A10-1)),M9) -> 14995.337 | N10: =MAX((Inputs!G$25*POWER(1+(Inputs!$C$3-(Inputs!$C$3*(('Steady State'!$A10-1)/Inputs!$C$4))),'Steady State'!$A10-1)),N9) -> 6426.573 | O10: 0 | P10: 0
A11: 9 | C11: =H11+M11 -> 512716.58 | D11: =I11+N11 -> 348095.28 | E11: =J11+O11 -> 22236.024 | F11: =(K11+P11)-F10 -> 31756.148 | H11: {=MMULT($C10:$F10,P_Matrix)} -> 497575.79 | I11: 341606.37 | J11: 22236.024 | K11: 63911.206 | M11: =MAX((Inputs!F$25*POWER(1+(Inputs!$C$3-(Inputs!$C$3*(('Steady State'!$A11-1)/Inputs!$C$4))),'Steady State'!$A11-1)),M10) -> 15140.792 | N11: =MAX((Inputs!G$25*POWER(1+(Inputs!$C$3-(Inputs!$C$3*(('Steady State'!$A11-1)/Inputs!$C$4))),'Steady State'!$A11-1)),N10) -> 6488.9108 | O11: 0 | P11: 0
A12: 10 | C12: =H12+M12 -> 502945.19 | D12: =I12+N12 -> 348608.24 | E12: =J12+O12 -> 21949.733 | F12: =(K12+P12)-F11 -> 31383.362 | H12: {=MMULT($C11:$F11,P_Matrix)} -> 487658.14 | I12: 342056.65 | J12: 21949.733 | K12: 63139.51 | M12: =MAX((Inputs!F$25*POWER(1+(Inputs!$C$3-(Inputs!$C$3*(('Steady State'!$A12-1)/Inputs!$C$4))),'Steady State'!$A12-1)),M11) -> 15287.052 | N12: =MAX((Inputs!G$25*POWER(1+(Inputs!$C$3-(Inputs!$C$3*(('Steady State'!$A12-1)/Inputs!$C$4))),'Steady State'!$A12-1)),N11) -> 6551.5938 | O12: 0 | P12: 0
A13: 11 | C13: =H13+M13 -> 493883.65 | D13: =I13+N13 -> 348948.84 | E13: =J13+O13 -> 21685.374 | F13: =(K13+P13)-F12 -> 31034.036 | H13: {=MMULT($C12:$F12,P_Matrix)} -> 478449.53 | I13: 342334.22 | J13: 21685.374 | K13: 62417.398 | M13: =MAX((Inputs!F$25*POWER(1+(Inputs!$C$3-(Inputs!$C$3*(('Steady State'!$A13-1)/Inputs!$C$4))),'Steady State'!$A13-1)),M12) -> 15434.114 | N13: =MAX((Inputs!G$25*POWER(1+(Inputs!$C$3-(Inputs!$C$3*(('Steady State'!$A13-1)/Inputs!$C$4))),'Steady State'!$A13-1)),N12) -> 6614.6202 | O13: 0 | P13: 0
A14: 12 | C14: =H14+M14 -> 485490.63 | D14: =I14+N14 -> 349141.33 | E14: =J14+O14 -> 21439.549 | F14: =(K14+P14)-F13 -> 30706.318 | H14: {=MMULT($C13:$F13,P_Matrix)} -> 469908.66 | I14: 342463.34 | J14: 21439.549 | K14: 61740.355 | M14: =MAX((Inputs!F$25*POWER(1+(Inputs!$C$3-(Inputs!$C$3*(('Steady State'!$A14-1)/Inputs!$C$4))),'Steady State'!$A14-1)),M13) -> 15581.973 | N14: =MAX((Inputs!G$25*POWER(1+(Inputs!$C$3-(Inputs!$C$3*(('Steady State'!$A14-1)/Inputs!$C$4))),'Steady State'!$A14-1)),N13) -> 6677.9884 | O14: 0 | P14: 0
A15: 13 | C15: =H15+M15 -> 477727.18 | D15: =I15+N15 -> 349207.75 | E15: =J15+O15 -> 21210.049 | F15: =(K15+P15)-F14 -> 30398.846 | H15: {=MMULT($C14:$F14,P_Matrix)} -> 461996.56 | I15: 342466.05 | J15: 21210.049 | K15: 61105.164 | M15: =MAX((Inputs!F$25*POWER(1+(Inputs!$C$3-(Inputs!$C$3*(('Steady State'!$A15-1)/Inputs!$C$4))),'Steady State'!$A15-1)),M14) -> 15730.625 | N15: =MAX((Inputs!G$25*POWER(1+(Inputs!$C$3-(Inputs!$C$3*(('Steady State'!$A15-1)/Inputs!$C$4))),'Steady State'!$A15-1)),N14) -> 6741.6966 | O15: 0 | P15: 0
A16: 14 | C16: =H16+M16 -> 470556.7 | D16: =I16+N16 -> 349168.15 | E16: =J16+O16 -> 20995.379 | F16: =(K16+P16)-F15 -> 30110.56 | H16: {=MMULT($C15:$F15,P_Matrix)} -> 454676.64 | I16: 342362.41 | J16: 20995.379 | K16: 60509.406 | M16: =MAX((Inputs!F$25*POWER(1+(Inputs!$C$3-(Inputs!$C$3*(('Steady State'!$A16-1)/Inputs!$C$4))),'Steady State'!$A16-1)),M15) -> 15880.067 | N16: =MAX((Inputs!G$25*POWER(1+(Inputs!$C$3-(Inputs!$C$3*(('Steady State'!$A16-1)/Inputs!$C$4))),'Steady State'!$A16-1)),N15) -> 6805.7429 | O16: 0 | P16: 0
... A1001: 999 | C1001: =H1001+M1001 -> 1038704.5 | D1001: =I1001+N1001 -> 881013.41 | E1001: =J1001+O1001 -> 47992.949 | F1001: =(K1001+P1001)-F1000 -> 69589.775 | H1001: {=MMULT($C1000:$F1000,P_Matrix)} -> 989991.69 | I1001: 860136.48 | J1001: 47992.949 | K1001: 139179.55 | M1001: =MAX((Inputs!F$25*POWER(1+(Inputs!$C$3-(Inputs!$C$3*(('Steady State'!$A1001-1)/Inputs!$C$4))),'Steady State'!$A1001-1)),M1000) -> 48712.843 | N1001: =MAX((Inputs!G$25*POWER(1+(Inputs!$C$3-(Inputs!$C$3*(('Steady State'!$A1001-1)/Inputs!$C$4))),'Steady State'!$A1001-1)),N1000) -> 20876.933 | O1001: 0 | P1001: 0
A1002: 1000 | C1002: =H1002+M1002 -> 1038704.5 | D1002: =I1002+N1002 -> 881013.41 | E1002: =J1002+O1002 -> 47992.949 | F1002: =(K1002+P1002)-F1001 -> 69589.775 | G1002: =IF(AND(INT(F1001)=INT(F1002),INT(E1001)=INT(E1002),INT(D1001)=INT(D1002),INT(C1001)=INT(C1002)),1,0) -> 1 | H1002: {=MMULT($C1001:$F1001,P_Matrix)} -> 989991.69 | I1002: 860136.48 | J1002: 47992.949 | K1002: 139179.55 | M1002: =MAX((Inputs!F$25*POWER(1+(Inputs!$C$3-(Inputs!$C$3*(('Steady State'!$A1002-1)/Inputs!$C$4))),'Steady State'!$A1002-1)),M1001) -> 48712.843 | N1002: =MAX((Inputs!G$25*POWER(1+(Inputs!$C$3-(Inputs!$C$3*(('Steady State'!$A1002-1)/Inputs!$C$4))),'Steady State'!$A1002-1)),N1001) -> 20876.933 | O1002: 0 | P1002: 0

Sheet Risk Metrics
A1: Outputs
A2: Month | B2: 10
A3: Revenue | B3: Monthly Revenue from Basic Plans | C3: =VLOOKUP($B$2,'Steady State'!A:F,3)*BasicPlanPrice -> 7544177.9
B4: Monthly Revenue from Premium Plans | C4: =VLOOKUP($B$2,'Steady State'!A:F,4)*PremiumPlanPrice -> 7669381.4 | N4: =_xlfn.CONCAT("Potential Growth After Month ",B2) -> Potential Growth After Month 10
B5: Total Monthly Revenue | C5: =C3+C4 -> 15213559 | N5: Current ARR | O5: =C6 -> 1.8256271e+08
B6: Total Annual Revenue | C6: =C5*12 -> 1.8256271e+08 | N6: Growth Opportunity | O6: =O7-O5 -> 2.3699165e+08
B7: Blended Average Revenue Per Customer | C7: =C5/(VLOOKUP(B2,'Steady State'!A:D,3)+VLOOKUP(B2,'Steady State'!A:D,4)) -> 17.865654 | N7: Terminal Cap | O7: =C22 -> 4.1955436e+08
B8: =_xlfn.CONCAT("Gross Margin (In month ",B2,")") -> Gross Margin (In month 10) | C8: =GrossMarginPercent*C5 -> 6846101.7 | F8: Did we find a Terminal Value? | G8: =IF('Steady State'!$G$1002=1,"Yes","No") -> Yes
B9: =_xlfn.CONCAT("Acquisition Spend (In month ",$B$2,")") -> Acquisition Spend (In month 10) | C9: =IFERROR(CAC*(VLOOKUP(B2,'Steady State'!A:P,13)+VLOOKUP(B2,'Steady State'!A:P,14)),"Cannot be Calculated") -> 2620637.5 | F9: What is it?
F10: =IF($G$8="Yes","Basic Plan","Could not be calculated") -> Basic Plan | G10: =IF($G$8="Yes","Premium Plan","") -> Premium Plan | H10: =IF($G$8="Yes","Inactive","") -> Inactive | I10: =IF($G$8="Yes","Churned","") -> Churned
F11: =IF($G$8="Yes",'Steady State'!C1002,"") -> 1038704.5 | G11: =IF($G$8="Yes",'Steady State'!D1002,"") -> 881013.41 | H11: =IF($G$8="Yes",'Steady State'!E1002,"") -> 47992.949 | I11: =IF($G$8="Yes",'Steady State'!F1002,"") -> 69589.775
A12: Saturation
A13: Month | B13: 10 | F13: =IF($G$8="Yes","Basic Plan Share","") -> Basic Plan Share | G13: =IF($G$8="Yes",F11/(F11+G11),"") -> 0.54107143
F14: =IF($G$8="Yes","Premium Plan Share","") -> Premium Plan Share | G14: =IF($G$8="Yes",G11/(F11+G11),"") -> 0.45892857
B15: Basic Plan | C15: Premium Plan | D15: Total
A16: =_xlfn.CONCAT("Number of Subscribers in Month ",B13) -> Number of Subscribers in Month 10 | B16: =VLOOKUP(B13,'Steady State'!A:D,3) -> 502945.19 | C16: =VLOOKUP(B13,'Steady State'!A:D,4) -> 348608.24 | D16: =B16+C16 -> 851553.43
A17: Potential Subscribers Reached | B17: =VLOOKUP(B13,'Steady State'!A:D,3)/F11 -> 0.48420429 | C17: =VLOOKUP(B13,'Steady State'!A:D,4)/G11 -> 0.39569005 | D17: =(VLOOKUP(B13,'Steady State'!A:D,3)+VLOOKUP(B13,'Steady State'!A:D,4))/(F11+G11) -> 0.44358258
A19: Terminal Revenue Cap | B19: Basic Revenue Cap | C19: =F11*BasicPlanPrice -> 15580568
B20: Premium Revenue Cap | C20: =G11*PremiumPlanPrice -> 19382295
B21: Max Monthly Revenue Cap | C21: =C19+C20 -> 34962863
B22: Max Annual Revenue Cap | C22: =C21*12 -> 4.1955436e+08
